{
  "cli.app.title": "PhiFanmade 开源工具集 CLI",
  "cli.msg.loaded": "已经把小可爱谱面塞进 {workspace} 工作区啦！",
  "cli.msg.saved": "做好啦！把工作区 '{workspace}' 存到 '{path}' 了！",
  "cli.msg.cleared": "哗啦啦~ 所有工作区都打扫干净了喵！",
  "cli.msg.written": "写好了哟！{path}",
  "cli.msg.help": "详见README.md喵！",
  "cli.warn.rpe.convert": "RPE 转换还在化妆中，稍等一下下~",
  "cli.err.unknown": "咦？这条指令我还不认识呢，试试 'version' 或看看 README 喵~",
  "cli.err.unimplemented":"这个命令功能还未完全实现呢...",
  "cli.err.input.required": "需要提供 --input 哟，或者用 --workspace 也可以~",
  "cli.err.output.required": "需要提供 --output 才能帮你保存呢~",
  "cli.err.workspace.missing": "没有找到工作区 {workspace} 喵..."
}
